pyfortified_requests/__init__.py
pyfortified_requests/pyfortified_requests.py
pyfortified_requests/pyfortified_requests_download.py
pyfortified_requests/pyfortified_requests_upload.py
pyfortified_requests/errors/__init__.py
pyfortified_requests/errors/error_codes.py
pyfortified_requests/errors/error_desc.py
pyfortified_requests/errors/errors_traceback.py
pyfortified_requests/exceptions/__init__.py
pyfortified_requests/exceptions/base.py
pyfortified_requests/exceptions/custom.py
pyfortified_requests/support/__init__.py
pyfortified_requests/support/bom_encoding.py
pyfortified_requests/support/constants.py
pyfortified_requests/support/curl.py
pyfortified_requests/support/metrics.py
pyfortified_requests/support/requests_session_client.py
pyfortified_requests/support/retry_exception.py
pyfortified_requests/support/usage.py
pyfortified_requests/support/utils.py
pyfortified_requests/support/response/__init__.py
pyfortified_requests/support/response/csv.py
pyfortified_requests/support/response/parse.py
pyfortified_requests/support/response/validate.py
pyfortified_requests-0.3.6.dist-info/METADATA
pyfortified_requests-0.3.6.dist-info/RECORD
pyfortified_requests-0.3.6.dist-info/WHEEL
pyfortified_requests-0.3.6.dist-info/top_level.txt
