Metadata-Version: 2.1
Name: pyfortified-requests
Version: 0.3.6
Summary: Extension to Python `requests` functionality.
Home-page: https://github.com/jeff00seattle/pyfortified-requests
Author: UNKNOWN
Author-email: UNKNOWN
License: MIT License
Download-URL: https://github.com/jeff00seattle/pyfortified-requests/archive/v0.3.6.tar.gz
Keywords: pyfortified requests
Platform: UNKNOWN
Classifier: Development Status :: 3 - Alpha
Classifier: Intended Audience :: Developers
Classifier: Natural Language :: English
Classifier: License :: OSI Approved :: MIT License
Classifier: Operating System :: OS Independent
Classifier: Natural Language :: English
Classifier: Programming Language :: Python
Classifier: Programming Language :: Python :: 3
Classifier: Programming Language :: Python :: 3.4
Classifier: Programming Language :: Python :: 3.5
Classifier: Programming Language :: Python :: 3.6
Classifier: Topic :: Software Development :: Libraries :: Python Modules
Requires-Dist: beautifulsoup4 (>=4.5.3)
Requires-Dist: DateTime (>=4.1.1)
Requires-Dist: deepdiff (>=3.3.0)
Requires-Dist: pprintpp (>=0.3.0)
Requires-Dist: psutil (>=5.0.1)
Requires-Dist: pyfortified-logging (>=0.1.8)
Requires-Dist: pyhttpstatus-utils (==0.3.3)
Requires-Dist: pymemcache-client (==0.3.2)
Requires-Dist: pytest-cov (>=2.5.1)
Requires-Dist: pytest-flask (>=0.10.0)
Requires-Dist: pytest-forked (>=0.2)
Requires-Dist: pytest-httpbin (>=0.3.0)
Requires-Dist: pytest-mock (>=1.10.0)
Requires-Dist: pytest-xdist (>=1.22.2)
Requires-Dist: pytest (>=3.5.1)
Requires-Dist: python-dateutil (>=2.6.0)
Requires-Dist: requests-mock (>=1.4.0)
Requires-Dist: requests-toolbelt (>=0.8.0)
Requires-Dist: requests (>=2.18.4)
Requires-Dist: safe-cast (>=0.3.0)
Requires-Dist: six (>=1.10.0)
Requires-Dist: tzlocal (>=1.3)
Requires-Dist: ujson (>=1.35)
Requires-Dist: wheel (>=0.29.0)
Requires-Dist: xmltodict (>=0.10.2)
